badredos/__init__.py
badredos/main.py
badredos-1.0.0.dist-info/METADATA
badredos-1.0.0.dist-info/WHEEL
badredos-1.0.0.dist-info/entry_points.txt
badredos-1.0.0.dist-info/top_level.txt
badredos-1.0.0.dist-info/RECORD
