Metadata-Version: 2.1
Name: badredos
Version: 1.0.0
Summary: A sample package with an entry point
Author: ctrlaltdelete
Author-email: my@email.com
License: MIT
